pyprotogen/__init__.py
pyprotogen/dependencies/__init__.py
pyprotogen/dependencies/interceptors/__init__.py
pyprotogen/dependencies/interceptors/client_logging.py
pyprotogen/dependencies/interceptors/dto.py
pyprotogen/dependencies/interceptors/metadata.py
pyprotogen/dependencies/interceptors/utils.py
pyprotogen/dependencies/server.py
pyprotogen/main.py
pyprotogen/packager.py
pyprotogen/renderer.py
pyprotogen/settings.py
pyprotogen/templates/client-py.j2
pyprotogen/templates/init-py.j2
pyprotogen/templates/pyproject-toml.j2
pyprotogen-0.0.27.dist-info/METADATA
pyprotogen-0.0.27.dist-info/WHEEL
pyprotogen-0.0.27.dist-info/entry_points.txt
pyprotogen-0.0.27.dist-info/licenses/LICENSE
pyprotogen-0.0.27.dist-info/RECORD
