Metadata-Version: 2.4
Name: pyprotogen
Version: 0.0.27
Summary: 
License-File: LICENSE
Author: Sergio Soldatov
Author-email: soldatovsr97@gmail.com
Requires-Python: >=3.11,<4.0
Classifier: Programming Language :: Python :: 3
Classifier: Programming Language :: Python :: 3.11
Classifier: Programming Language :: Python :: 3.12
Classifier: Programming Language :: Python :: 3.13
Classifier: Programming Language :: Python :: 3.14
Requires-Dist: grpc-prometheus-metrics (==0.0.5)
Requires-Dist: grpcio-tools (==1.59.3)
Requires-Dist: jinja2 (>=3.1.1,<4.0.0)
Requires-Dist: mypy-protobuf (==3.4.0)
Requires-Dist: opentelemetry-instrumentation-grpc (==0.37b)
Requires-Dist: orjson (>=3.8.7,<4.0.0)
Requires-Dist: protobuf (==4.22.1)
Requires-Dist: typer (>=0.4.1,<0.5.0)
Project-URL: Repository, https://github.com/sollof/pyprotogen
